test_poetry_demo/__init__.py
test_poetry_demo/validator.py
test_poetry_demo-0.1.0.dist-info/METADATA
test_poetry_demo-0.1.0.dist-info/WHEEL
test_poetry_demo-0.1.0.dist-info/RECORD
