Metadata-Version: 2.1
Name: test-poetry-demo
Version: 0.1.0
Summary: 
Author: Manikandan B
Author-email: manikandan@10decoders.com
Requires-Python: >=3.12,<4.0
Classifier: Programming Language :: Python :: 3
Classifier: Programming Language :: Python :: 3.12
Requires-Dist: requests (>=2.32.3,<3.0.0)
